response_differ/Config_store.py
response_differ/__init__.py
response_differ/cassetes/__init__.py
response_differ/cassetes/serializer.py
response_differ/cassetes/vcr.py
response_differ/cheks.py
response_differ/exceptions.py
response_differ/play.py
response_differ/response_diff/__init__.py
response_differ/response_diff/cli.py
response_differ-0.2.8.dist-info/entry_points.txt
response_differ-0.2.8.dist-info/WHEEL
response_differ-0.2.8.dist-info/METADATA
response_differ-0.2.8.dist-info/RECORD
