Metadata-Version: 2.1
Name: response-differ
Version: 0.2.8
Summary: 
Author: vkytepov
Author-email: vkytepov@live.com
Requires-Python: >=3.8,<4.0
Classifier: Programming Language :: Python :: 3
Classifier: Programming Language :: Python :: 3.8
Classifier: Programming Language :: Python :: 3.9
Requires-Dist: PyYAML (>=5.4.1,<6.0.0)
Requires-Dist: click (>=7.1.2,<8.0.0)
Requires-Dist: click-config-file (>=0.6.0,<0.7.0)
Requires-Dist: deepdiff (>=5.3.0,<6.0.0)
Requires-Dist: grpc_requests (>=0.0.10,<0.0.11)
Requires-Dist: requests (>=2.25.1,<3.0.0)
Requires-Dist: vcrpy (>=4.1.1,<5.0.0)
